tests/__init__.py
tests/test_counterfactual_regression.py
tests/test_counterfactual_search.py
tests/test_counterfactual_spiral.py
tests/test_dataset_read.py
tests/test_diffusion.py
tests/test_entire_pipeline_gp.py
tests/test_gp_expression.py
tests/test_homeloan_coherence.py
tests/test_instance_creation.py
tests/test_normalization.py
tests/test_reading_model.py
tests/test_swiss_roll.py
tests/test_train_model.py
trustce/__init__.py
trustce/cfsearch.py
trustce/config.py
trustce/dataset.py
trustce/dataset_metadata.py
trustce/explainable_model.py
trustce/explainer.py
trustce/feature_manager.py
trustce/load_datasets.py
trustce/optim_config.py
trustce/setup.py
trustce/train.py
trustce/transformer.py
trustce/cefeature/__init__.py
trustce/cefeature/feature_sampler.py
trustce/ceinstance/__init__.py
trustce/ceinstance/instance_factory.py
trustce/ceinstance/instance_sampler.py
trustce-0.2.9.data/data/LICENSE
trustce-0.2.9.data/data/README.md
trustce-0.2.9.dist-info/LICENSE
trustce-0.2.9.dist-info/METADATA
trustce-0.2.9.dist-info/WHEEL
trustce-0.2.9.dist-info/top_level.txt
trustce-0.2.9.dist-info/RECORD
